[{"dateTime": "2019-11-10 00:00:00", "value": "0"}, {"dateTime": "2019-11-11 00:00:00", "value": "159"}, {"dateTime": "2019-11-12 00:00:00", "value": "209"}, {"dateTime": "2019-11-13 00:00:00", "value": "269"}, {"dateTime": "2019-11-14 00:00:00", "value": "199"}, {"dateTime": "2019-11-15 00:00:00", "value": "184"}, {"dateTime": "2019-11-16 00:00:00", "value": "130"}, {"dateTime": "2019-11-17 00:00:00", "value": "201"}, {"dateTime": "2019-11-18 00:00:00", "value": "213"}, {"dateTime": "2019-11-19 00:00:00", "value": "238"}, {"dateTime": "2019-11-20 00:00:00", "value": "194"}, {"dateTime": "2019-11-21 00:00:00", "value": "281"}, {"dateTime": "2019-11-22 00:00:00", "value": "178"}, {"dateTime": "2019-11-23 00:00:00", "value": "193"}, {"dateTime": "2019-11-24 00:00:00", "value": "268"}, {"dateTime": "2019-11-25 00:00:00", "value": "240"}, {"dateTime": "2019-11-26 00:00:00", "value": "217"}, {"dateTime": "2019-11-27 00:00:00", "value": "194"}, {"dateTime": "2019-11-28 00:00:00", "value": "230"}, {"dateTime": "2019-11-29 00:00:00", "value": "258"}, {"dateTime": "2019-11-30 00:00:00", "value": "240"}, {"dateTime": "2019-12-01 00:00:00", "value": "253"}, {"dateTime": "2019-12-02 00:00:00", "value": "325"}, {"dateTime": "2019-12-03 00:00:00", "value": "223"}, {"dateTime": "2019-12-04 00:00:00", "value": "176"}, {"dateTime": "2019-12-05 00:00:00", "value": "179"}, {"dateTime": "2019-12-06 00:00:00", "value": "197"}, {"dateTime": "2019-12-07 00:00:00", "value": "276"}, {"dateTime": "2019-12-08 00:00:00", "value": "185"}, {"dateTime": "2019-12-09 00:00:00", "value": "240"}, {"dateTime": "2019-12-10 00:00:00", "value": "243"}, {"dateTime": "2019-12-11 00:00:00", "value": "201"}, {"dateTime": "2019-12-12 00:00:00", "value": "282"}, {"dateTime": "2019-12-13 00:00:00", "value": "49"}, {"dateTime": "2019-12-14 00:00:00", "value": "0"}, {"dateTime": "2019-12-15 00:00:00", "value": "0"}, {"dateTime": "2019-12-16 00:00:00", "value": "0"}, {"dateTime": "2019-12-17 00:00:00", "value": "112"}, {"dateTime": "2019-12-18 00:00:00", "value": "256"}, {"dateTime": "2019-12-19 00:00:00", "value": "376"}, {"dateTime": "2019-12-20 00:00:00", "value": "259"}, {"dateTime": "2019-12-21 00:00:00", "value": "276"}, {"dateTime": "2019-12-22 00:00:00", "value": "276"}, {"dateTime": "2019-12-23 00:00:00", "value": "268"}, {"dateTime": "2019-12-24 00:00:00", "value": "299"}, {"dateTime": "2019-12-25 00:00:00", "value": "142"}, {"dateTime": "2019-12-26 00:00:00", "value": "174"}, {"dateTime": "2019-12-27 00:00:00", "value": "219"}, {"dateTime": "2019-12-28 00:00:00", "value": "341"}, {"dateTime": "2019-12-29 00:00:00", "value": "227"}, {"dateTime": "2019-12-30 00:00:00", "value": "127"}, {"dateTime": "2019-12-31 00:00:00", "value": "232"}, {"dateTime": "2020-01-01 00:00:00", "value": "146"}, {"dateTime": "2020-01-02 00:00:00", "value": "166"}, {"dateTime": "2020-01-03 00:00:00", "value": "241"}, {"dateTime": "2020-01-04 00:00:00", "value": "227"}, {"dateTime": "2020-01-05 00:00:00", "value": "196"}, {"dateTime": "2020-01-06 00:00:00", "value": "265"}, {"dateTime": "2020-01-07 00:00:00", "value": "209"}, {"dateTime": "2020-01-08 00:00:00", "value": "202"}, {"dateTime": "2020-01-09 00:00:00", "value": "201"}, {"dateTime": "2020-01-10 00:00:00", "value": "225"}, {"dateTime": "2020-01-11 00:00:00", "value": "225"}, {"dateTime": "2020-01-12 00:00:00", "value": "112"}, {"dateTime": "2020-01-13 00:00:00", "value": "67"}, {"dateTime": "2020-01-14 00:00:00", "value": "132"}, {"dateTime": "2020-01-15 00:00:00", "value": "206"}, {"dateTime": "2020-01-16 00:00:00", "value": "194"}, {"dateTime": "2020-01-17 00:00:00", "value": "234"}, {"dateTime": "2020-01-18 00:00:00", "value": "148"}, {"dateTime": "2020-01-19 00:00:00", "value": "147"}, {"dateTime": "2020-01-20 00:00:00", "value": "201"}, {"dateTime": "2020-01-21 00:00:00", "value": "257"}, {"dateTime": "2020-01-22 00:00:00", "value": "284"}, {"dateTime": "2020-01-23 00:00:00", "value": "278"}, {"dateTime": "2020-01-24 00:00:00", "value": "209"}, {"dateTime": "2020-01-25 00:00:00", "value": "265"}, {"dateTime": "2020-01-26 00:00:00", "value": "275"}, {"dateTime": "2020-01-27 00:00:00", "value": "277"}, {"dateTime": "2020-01-28 00:00:00", "value": "315"}, {"dateTime": "2020-01-29 00:00:00", "value": "282"}, {"dateTime": "2020-01-30 00:00:00", "value": "248"}, {"dateTime": "2020-01-31 00:00:00", "value": "215"}, {"dateTime": "2020-02-01 00:00:00", "value": "157"}, {"dateTime": "2020-02-02 00:00:00", "value": "203"}, {"dateTime": "2020-02-03 00:00:00", "value": "246"}, {"dateTime": "2020-02-04 00:00:00", "value": "208"}, {"dateTime": "2020-02-05 00:00:00", "value": "277"}, {"dateTime": "2020-02-06 00:00:00", "value": "194"}, {"dateTime": "2020-02-07 00:00:00", "value": "266"}, {"dateTime": "2020-02-08 00:00:00", "value": "199"}, {"dateTime": "2020-02-09 00:00:00", "value": "181"}, {"dateTime": "2020-02-10 00:00:00", "value": "254"}, {"dateTime": "2020-02-11 00:00:00", "value": "263"}, {"dateTime": "2020-02-12 00:00:00", "value": "296"}, {"dateTime": "2020-02-13 00:00:00", "value": "232"}, {"dateTime": "2020-02-14 00:00:00", "value": "287"}, {"dateTime": "2020-02-15 00:00:00", "value": "196"}, {"dateTime": "2020-02-16 00:00:00", "value": "280"}, {"dateTime": "2020-02-17 00:00:00", "value": "402"}, {"dateTime": "2020-02-18 00:00:00", "value": "194"}, {"dateTime": "2020-02-19 00:00:00", "value": "262"}, {"dateTime": "2020-02-20 00:00:00", "value": "368"}, {"dateTime": "2020-02-21 00:00:00", "value": "341"}, {"dateTime": "2020-02-22 00:00:00", "value": "173"}, {"dateTime": "2020-02-23 00:00:00", "value": "136"}, {"dateTime": "2020-02-24 00:00:00", "value": "328"}, {"dateTime": "2020-02-25 00:00:00", "value": "182"}, {"dateTime": "2020-02-26 00:00:00", "value": "216"}, {"dateTime": "2020-02-27 00:00:00", "value": "260"}, {"dateTime": "2020-02-28 00:00:00", "value": "198"}, {"dateTime": "2020-02-29 00:00:00", "value": "162"}, {"dateTime": "2020-03-01 00:00:00", "value": "168"}, {"dateTime": "2020-03-02 00:00:00", "value": "295"}, {"dateTime": "2020-03-03 00:00:00", "value": "223"}, {"dateTime": "2020-03-04 00:00:00", "value": "309"}, {"dateTime": "2020-03-05 00:00:00", "value": "283"}, {"dateTime": "2020-03-06 00:00:00", "value": "324"}, {"dateTime": "2020-03-07 00:00:00", "value": "211"}, {"dateTime": "2020-03-08 00:00:00", "value": "212"}, {"dateTime": "2020-03-09 00:00:00", "value": "302"}, {"dateTime": "2020-03-10 00:00:00", "value": "243"}, {"dateTime": "2020-03-11 00:00:00", "value": "216"}, {"dateTime": "2020-03-12 00:00:00", "value": "271"}, {"dateTime": "2020-03-13 00:00:00", "value": "160"}, {"dateTime": "2020-03-14 00:00:00", "value": "255"}, {"dateTime": "2020-03-15 00:00:00", "value": "214"}, {"dateTime": "2020-03-16 00:00:00", "value": "224"}, {"dateTime": "2020-03-17 00:00:00", "value": "217"}, {"dateTime": "2020-03-18 00:00:00", "value": "163"}, {"dateTime": "2020-03-19 00:00:00", "value": "132"}, {"dateTime": "2020-03-20 00:00:00", "value": "120"}, {"dateTime": "2020-03-21 00:00:00", "value": "185"}, {"dateTime": "2020-03-22 00:00:00", "value": "142"}, {"dateTime": "2020-03-23 00:00:00", "value": "202"}, {"dateTime": "2020-03-24 00:00:00", "value": "167"}, {"dateTime": "2020-03-25 00:00:00", "value": "174"}, {"dateTime": "2020-03-26 00:00:00", "value": "143"}, {"dateTime": "2020-03-27 00:00:00", "value": "100"}, {"dateTime": "2020-03-28 00:00:00", "value": "175"}, {"dateTime": "2020-03-29 00:00:00", "value": "127"}, {"dateTime": "2020-03-30 00:00:00", "value": "179"}, {"dateTime": "2020-03-31 00:00:00", "value": "169"}]